{"Description": "あなたはロンドンではどこに帽子を掛けるんだい？@{I}貴方はロンドンの何処を拠点にしている？@{M}Where do you hang your hat in London?",
 "LevelDescriptionText": "1|盲た操舵手亭の上の部屋~2|優雅な邸宅~3|浜辺の豪邸@{I}1|盲た操舵手亭の上の部屋~2|優美な邸宅~3|ジーサイドの館@{M}$Blind Helmsman -> 盲た操舵手亭, Elegant Townhouse -> 優雅な邸宅, Zeeside Mansion -> 浜辺の豪邸$1|A Room above the Blind Helmsman~2|An Elegant Townhouse~3|A Zeeside Mansion",
 "ChangeDescriptionText": "1|あなたは現在、盲た操舵手亭の上の部屋で寝泊まりしている。~2|あなたは現在、優雅な邸宅で寝泊まりしている。~3|あなたは現在、浜辺の豪邸で寝泊まりしている。@{I}1|貴方は現在盲た操舵手亭の上の部屋を宿場にしている。~2|貴方は現在優美な邸宅を宿場にしている。~3|貴方は現在ジーサイドの館を宿場にしている。@{M}$Blind Helmsman -> 盲た操舵手亭, Elegant Townhouse -> 優雅な邸宅, Zeeside Mansion -> 浜辺の豪邸$1|You now lodge in a Room above the Blind Helmsman.~2|You now lodge in an Elegant Townhouse.~3|You now lodge in a Zeeside Mansion.",
 "Name": "記憶: 宿の質@{I}回顧録: 宿場の質@{M}$Memoirs: -> 記憶:$Memoirs: Quality of Lodgings",
 "Id": 108290}
